<?xml version="1.0" encoding="utf-8"?>
<!DOCTYPE chapter PUBLIC "-//OASIS//DTD DocBook XML V4.5//EN" "file://zonbook/docbookx.dtd"
[
    <!ENTITY % xinclude SYSTEM "file://AWSShared/common/xinclude.mod">
    %xinclude;
    <!ENTITY % phrases-shared SYSTEM "file://AWSShared/common/phrases-shared.ent">
    %phrases-shared;
    <!ENTITY % phrases-appmesh SYSTEM "../shared/phrases-app-mesh.ent"> 
    %phrases-appmesh;  
]>
<example>
  <title>JSON for &ECS; task definition - EC2 launch type</title>
  <programlisting language="json">{
  "family": "<replaceable>taskB</replaceable>",
  "memory": "<replaceable>256</replaceable>",
  "proxyConfiguration": {
    "type": "APPMESH",
    "containerName": "envoy",
    "properties": [
      {
        "name": "IgnoredUID",
        "value": "<replaceable>1337</replaceable>"
      },
      {
        "name": "ProxyIngressPort",
        "value": "15000"
      },
      {
        "name": "ProxyEgressPort",
        "value": "15001"
      },
      {
        "name": "AppPorts",
        "value": "<replaceable>9080</replaceable>"
      },
      {
        "name": "EgressIgnoredIPs",
        "value": "169.254.170.2,169.254.169.254"
      },
      {
        "name": "EgressIgnoredPorts",
        "value": "<replaceable>22</replaceable>"
      }
    ]
  },
  "containerDefinitions": [
    {
      "name": "<replaceable>appName</replaceable>",
      "image": "<replaceable>appImage</replaceable>",
      "portMappings": [
        {
          "containerPort": <replaceable>9080</replaceable>,
          "hostPort": <replaceable>9080</replaceable>,
          "protocol": "tcp"
        }
      ],
      "essential": true,
      "dependsOn": [
        {
          "containerName": "envoy",
          "condition": "HEALTHY"
        }
      ]
    },
    {
      "name": "envoy",
      "image": "&envoy-image-replaceable-registry;",
      "essential": true,
      "environment": [
        {
          "name": "APPMESH_VIRTUAL_NODE_NAME",
          "value": "mesh/<replaceable>apps</replaceable>/virtualNode/<replaceable>serviceB</replaceable>"
        }
      ],
      "healthCheck": {
        "command": [
          "CMD-SHELL",
          "curl -s http://localhost:9901/server_info | grep state | grep -q LIVE"
        ],
        "startPeriod": <replaceable>10</replaceable>,
        "interval": <replaceable>5</replaceable>,
        "timeout": <replaceable>2</replaceable>,
        "retries": <replaceable>3</replaceable>
      },
      "user": "<replaceable>1337</replaceable>"
    }
  ],
  "requiresCompatibilities" : [ "EC2" ],
  "taskRoleArn" : "arn:aws:iam::<replaceable>123456789012</replaceable>:role/<replaceable>ecsTaskRole</replaceable>",
  "executionRoleArn" : "arn:aws:iam::<replaceable>123456789012</replaceable>:role/<replaceable>ecsTaskExecutionRole</replaceable>",
  "networkMode": "awsvpc"
}</programlisting>
</example>
